acmdrunner
