Metadata-Version: 1.1
Name: acmdrunner
Version: 1.2
Summary: Ascetic command runner. The most ease way to power your python app with custom management commands
Home-page: https://github.com/sergeyglazyrindev/asceticcmdrunner
Author: Sergey Glazyrin
Author-email: sergey.glazyrin.dev@gmail.com
License: MIT
Download-URL: https://github.com/sergeyglazyrindev/asceticcmdrunner/tarball/1.2
Keywords: command,dispatch
Platform: UNKNOWN
Classifier: Development Status :: 4 - Beta
Classifier: Topic :: Software Development :: Libraries :: Application Frameworks
Classifier: Topic :: Software Development :: Libraries :: Python Modules
Classifier: Topic :: Utilities
Classifier: License :: OSI Approved :: MIT License
Classifier: Programming Language :: Python :: 2.7
Classifier: Programming Language :: Python :: 3
Classifier: Programming Language :: Python :: 3.1
Classifier: Programming Language :: Python :: 3.2
Classifier: Programming Language :: Python :: 3.3
Classifier: Programming Language :: Python :: 3.4
Classifier: Programming Language :: Python :: 3.5
Classifier: Intended Audience :: Developers
